{"total": {"lines":{"total":161,"covered":110,"skipped":0,"pct":68.32},"statements":{"total":174,"covered":112,"skipped":0,"pct":64.37},"functions":{"total":21,"covered":18,"skipped":0,"pct":85.71},"branches":{"total":74,"covered":34,"skipped":0,"pct":45.95}}
,"/Users/donald/Project/browser-image-compression/lib/image-compression.js": {"lines":{"total":32,"covered":23,"skipped":0,"pct":71.88},"functions":{"total":1,"covered":1,"skipped":0,"pct":100},"statements":{"total":32,"covered":23,"skipped":0,"pct":71.88},"branches":{"total":18,"covered":13,"skipped":0,"pct":72.22}}
,"/Users/donald/Project/browser-image-compression/lib/index.js": {"lines":{"total":26,"covered":22,"skipped":0,"pct":84.62},"functions":{"total":1,"covered":1,"skipped":0,"pct":100},"statements":{"total":26,"covered":22,"skipped":0,"pct":84.62},"branches":{"total":17,"covered":11,"skipped":0,"pct":64.71}}
,"/Users/donald/Project/browser-image-compression/lib/utils.js": {"lines":{"total":103,"covered":65,"skipped":0,"pct":63.11},"functions":{"total":19,"covered":16,"skipped":0,"pct":84.21},"statements":{"total":116,"covered":67,"skipped":0,"pct":57.76},"branches":{"total":39,"covered":10,"skipped":0,"pct":25.64}}
}
